Workbook

Sheet Raw Data
A1: E-Commerce Customer Experience Analytics — Raw Dataset
A2: 300+ realistic order records. Three intentional duplicate rows are included so data cleaning can be demonstrated.
A4: Order ID | B4: Order Date | C4: Category | D4: City | E4: Customer Age | F4: Order Value (₹) | G4: Discount (%) | H4: Expected Days | I4: Actual Days | J4: Payment Method | K4: Rating | L4: Cancelled | M4: Returned | N4: Distance (KM) | O4: Customer Type
A5: O0001 | B5: 46261 | C5: Electronics | D5: Bengaluru | E5: 35 | F5: 4243 | G5: 0 | H5: 4 | I5: 3 | J5: Net Banking | K5: 4 | L5: No | M5: No | N5: 3.8 | O5: Returning
A6: O0002 | B6: 46259 | C6: Fashion | D6: Hyderabad | E6: 55 | F6: 2293 | G6: 10 | H6: 2 | I6: 5 | J6: UPI | K6: 2 | L6: No | M6: No | N6: 21.6 | O6: New
A7: O0003 | B7: 46271 | C7: Electronics | D7: Delhi | E7: 40 | F7: 594 | G7: 25 | H7: 3 | I7: 3 | J7: Debit Card | K7: 4 | L7: No | M7: No | N7: 15.7 | O7: Returning
A8: O0004 | B8: 46258 | C8: Fashion | D8: Pune | E8: 22 | F8: 809 | G8: 0 | H8: 3 | I8: 3 | J8: Credit Card | K8: 5 | L8: No | M8: No | N8: 22 | O8: Returning
A9: O0005 | B9: 46249 | C9: Grocery | D9: Mumbai | E9: 35 | F9: 741 | G9: 0 | H9: 3 | I9: 3 | J9: Net Banking | K9: 4 | L9: No | M9: No | N9: 18.3 | O9: Returning
A10: O0006 | B10: 46260 | C10: Grocery | D10: Kolkata | E10: 21 | F10: 393 | G10: 5 | H10: 1 | I10: 1 | J10: Cash on Delivery | K10: 4 | L10: No | M10: No | N10: 22.8 | O10: New
A11: O0007 | B11: 46283 | C11: Home & Kitchen | D11: Mumbai | E11: 34 | F11: 3868 | G11: 20 | H11: 3 | I11: 4 | J11: UPI | K11: 4 | L11: No | M11: No | N11: 21.3 | O11: Returning
A12: O0008 | B12: 46235 | C12: Electronics | D12: Kolkata | E12: 25 | F12: 7378 | G12: 5 | H12: 3 | I12: 2 | J12: Net Banking | K12: 4 | L12: No | M12: No | N12: 22.5 | O12: New
A13: O0009 | B13: 46267 | C13: Electronics | D13: Pune | E13: 52 | F13: 4223 | G13: 10 | H13: 2 | I13: 3 | J13: Credit Card | K13: 4 | L13: No | M13: No | N13: 9.3 | O13: Returning
A14: O0010 | B14: 46266 | C14: Electronics | D14: Kolkata | E14: 37 | F14: 250 | G14: 25 | H14: 4 | I14: 5 | J14: Debit Card | K14: 4 | L14: No | M14: No | N14: 17.6 | O14: New
A15: O0011 | B15: 46243 | C15: Electronics | D15: Bengaluru | E15: 41 | F15: 7614 | G15: 10 | H15: 3 | I15: 2 | J15: Credit Card | K15: 4 | L15: No | M15: No | N15: 3 | O15: Returning
A16: O0012 | B16: 46277 | C16: Home & Kitchen | D16: Chennai | E16: 28 | F16: 1036 | G16: 10 | H16: 4 | I16: 4 | J16: Cash on Delivery | K16: 5 | L16: No | M16: No | N16: 24.6 | O16: Returning
... A307: O0175 | B307: 46271 | C307: Beauty | D307: Hyderabad | E307: 39 | F307: 807 | G307: 25 | H307: 3 | I307: 3 | J307: Cash on Delivery | K307: 5 | L307: No | M307: No | N307: 5.1 | O307: New

Sheet Project Roadmap
A1: PROJECT ROADMAP | B1: E-Commerce Customer Experience Analytics
A2: Business Question | B2: What factors are associated with delivery delays, low ratings, cancellations, and returns?
A3: Step 1 | B3: Use Raw Data sheet and remove duplicates in Excel.
A4: Step 2 | B4: Check for blanks, incorrect formats, and inconsistent categories.
A5: Step 3 | B5: Create calculated columns: Delivery Status, Delay Days, Rating Band, Order Outcome.
A6: Step 4 | B6: Use IF, SUM, AVERAGE, COUNTIF, SUMIF, AVERAGEIF and PivotTables.
A7: Step 5 | B7: Build 4–5 charts and a one-page dashboard.
A8: Step 6 | B8: Extract 4–6 business insights from the numbers.
A9: Step 7 | B9: Prepare a 10-slide presentation and speaking script.
A10: Tools | B10: Excel Online is enough for the main project. Python/Colab can be added later for extra analytics.

Sheet Cleaned Data
A1: Order ID | B1: Order Date | C1: Category | D1: City | E1: Customer Age | F1: Order Value (₹) | G1: Discount (%) | H1: Expected Days | I1: Actual Days | J1: Payment Method | K1: Rating | L1: Cancelled | M1: Returned | N1: Distance (KM) | O1: Customer Type | P1: Delivery Status | Q1: Delay Days | R1: Rating Band | S1: Order Outcome | T1: Net Sales | U1: Late Flag
A2: O0001 | B2: 46261 | C2: Electronics | D2: Bengaluru | E2: 35 | F2: 4243 | G2: 0 | H2: 4 | I2: 3 | J2: Net Banking | K2: 4 | L2: No | M2: No | N2: 3.8 | O2: Returning | P2: =IF(I2>H2,"Late","On Time") -> On Time | Q2: =MAX(0,I2-H2) -> 0 | R2: =IF(K2>=4,"High",IF(K2=3,"Medium","Low")) -> High | S2: =IF(L2="Yes","Cancelled",IF(M2="Yes","Returned","Completed")) -> Completed | T2: =F2*(1-G2/100) -> 4243 | U2: =IF(P2="Late",1,0) -> 0
A3: O0002 | B3: 46259 | C3: Fashion | D3: Hyderabad | E3: 55 | F3: 2293 | G3: 10 | H3: 2 | I3: 5 | J3: UPI | K3: 2 | L3: No | M3: No | N3: 21.6 | O3: New | P3: =IF(I3>H3,"Late","On Time") -> Late | Q3: =MAX(0,I3-H3) -> 3 | R3: =IF(K3>=4,"High",IF(K3=3,"Medium","Low")) -> Low | S3: =IF(L3="Yes","Cancelled",IF(M3="Yes","Returned","Completed")) -> Completed | T3: =F3*(1-G3/100) -> 2063.7 | U3: =IF(P3="Late",1,0) -> 1
A4: O0003 | B4: 46271 | C4: Electronics | D4: Delhi | E4: 40 | F4: 594 | G4: 25 | H4: 3 | I4: 3 | J4: Debit Card | K4: 4 | L4: No | M4: No | N4: 15.7 | O4: Returning | P4: =IF(I4>H4,"Late","On Time") -> On Time | Q4: =MAX(0,I4-H4) -> 0 | R4: =IF(K4>=4,"High",IF(K4=3,"Medium","Low")) -> High | S4: =IF(L4="Yes","Cancelled",IF(M4="Yes","Returned","Completed")) -> Completed | T4: =F4*(1-G4/100) -> 445.5 | U4: =IF(P4="Late",1,0) -> 0
A5: O0004 | B5: 46258 | C5: Fashion | D5: Pune | E5: 22 | F5: 809 | G5: 0 | H5: 3 | I5: 3 | J5: Credit Card | K5: 5 | L5: No | M5: No | N5: 22 | O5: Returning | P5: =IF(I5>H5,"Late","On Time") -> On Time | Q5: =MAX(0,I5-H5) -> 0 | R5: =IF(K5>=4,"High",IF(K5=3,"Medium","Low")) -> High | S5: =IF(L5="Yes","Cancelled",IF(M5="Yes","Returned","Completed")) -> Completed | T5: =F5*(1-G5/100) -> 809 | U5: =IF(P5="Late",1,0) -> 0
A6: O0005 | B6: 46249 | C6: Grocery | D6: Mumbai | E6: 35 | F6: 741 | G6: 0 | H6: 3 | I6: 3 | J6: Net Banking | K6: 4 | L6: No | M6: No | N6: 18.3 | O6: Returning | P6: =IF(I6>H6,"Late","On Time") -> On Time | Q6: =MAX(0,I6-H6) -> 0 | R6: =IF(K6>=4,"High",IF(K6=3,"Medium","Low")) -> High | S6: =IF(L6="Yes","Cancelled",IF(M6="Yes","Returned","Completed")) -> Completed | T6: =F6*(1-G6/100) -> 741 | U6: =IF(P6="Late",1,0) -> 0
A7: O0006 | B7: 46260 | C7: Grocery | D7: Kolkata | E7: 21 | F7: 393 | G7: 5 | H7: 1 | I7: 1 | J7: Cash on Delivery | K7: 4 | L7: No | M7: No | N7: 22.8 | O7: New | P7: =IF(I7>H7,"Late","On Time") -> On Time | Q7: =MAX(0,I7-H7) -> 0 | R7: =IF(K7>=4,"High",IF(K7=3,"Medium","Low")) -> High | S7: =IF(L7="Yes","Cancelled",IF(M7="Yes","Returned","Completed")) -> Completed | T7: =F7*(1-G7/100) -> 373.35 | U7: =IF(P7="Late",1,0) -> 0
A8: O0007 | B8: 46283 | C8: Home & Kitchen | D8: Mumbai | E8: 34 | F8: 3868 | G8: 20 | H8: 3 | I8: 4 | J8: UPI | K8: 4 | L8: No | M8: No | N8: 21.3 | O8: Returning | P8: =IF(I8>H8,"Late","On Time") -> Late | Q8: =MAX(0,I8-H8) -> 1 | R8: =IF(K8>=4,"High",IF(K8=3,"Medium","Low")) -> High | S8: =IF(L8="Yes","Cancelled",IF(M8="Yes","Returned","Completed")) -> Completed | T8: =F8*(1-G8/100) -> 3094.4 | U8: =IF(P8="Late",1,0) -> 1
A9: O0008 | B9: 46235 | C9: Electronics | D9: Kolkata | E9: 25 | F9: 7378 | G9: 5 | H9: 3 | I9: 2 | J9: Net Banking | K9: 4 | L9: No | M9: No | N9: 22.5 | O9: New | P9: =IF(I9>H9,"Late","On Time") -> On Time | Q9: =MAX(0,I9-H9) -> 0 | R9: =IF(K9>=4,"High",IF(K9=3,"Medium","Low")) -> High | S9: =IF(L9="Yes","Cancelled",IF(M9="Yes","Returned","Completed")) -> Completed | T9: =F9*(1-G9/100) -> 7009.1 | U9: =IF(P9="Late",1,0) -> 0
A10: O0009 | B10: 46267 | C10: Electronics | D10: Pune | E10: 52 | F10: 4223 | G10: 10 | H10: 2 | I10: 3 | J10: Credit Card | K10: 4 | L10: No | M10: No | N10: 9.3 | O10: Returning | P10: =IF(I10>H10,"Late","On Time") -> Late | Q10: =MAX(0,I10-H10) -> 1 | R10: =IF(K10>=4,"High",IF(K10=3,"Medium","Low")) -> High | S10: =IF(L10="Yes","Cancelled",IF(M10="Yes","Returned","Completed")) -> Completed | T10: =F10*(1-G10/100) -> 3800.7 | U10: =IF(P10="Late",1,0) -> 1
A11: O0010 | B11: 46266 | C11: Electronics | D11: Kolkata | E11: 37 | F11: 250 | G11: 25 | H11: 4 | I11: 5 | J11: Debit Card | K11: 4 | L11: No | M11: No | N11: 17.6 | O11: New | P11: =IF(I11>H11,"Late","On Time") -> Late | Q11: =MAX(0,I11-H11) -> 1 | R11: =IF(K11>=4,"High",IF(K11=3,"Medium","Low")) -> High | S11: =IF(L11="Yes","Cancelled",IF(M11="Yes","Returned","Completed")) -> Completed | T11: =F11*(1-G11/100) -> 187.5 | U11: =IF(P11="Late",1,0) -> 1
A12: O0011 | B12: 46243 | C12: Electronics | D12: Bengaluru | E12: 41 | F12: 7614 | G12: 10 | H12: 3 | I12: 2 | J12: Credit Card | K12: 4 | L12: No | M12: No | N12: 3 | O12: Returning | P12: =IF(I12>H12,"Late","On Time") -> On Time | Q12: =MAX(0,I12-H12) -> 0 | R12: =IF(K12>=4,"High",IF(K12=3,"Medium","Low")) -> High | S12: =IF(L12="Yes","Cancelled",IF(M12="Yes","Returned","Completed")) -> Completed | T12: =F12*(1-G12/100) -> 6852.6 | U12: =IF(P12="Late",1,0) -> 0
A13: O0012 | B13: 46277 | C13: Home & Kitchen | D13: Chennai | E13: 28 | F13: 1036 | G13: 10 | H13: 4 | I13: 4 | J13: Cash on Delivery | K13: 5 | L13: No | M13: No | N13: 24.6 | O13: Returning | P13: =IF(I13>H13,"Late","On Time") -> On Time | Q13: =MAX(0,I13-H13) -> 0 | R13: =IF(K13>=4,"High",IF(K13=3,"Medium","Low")) -> High | S13: =IF(L13="Yes","Cancelled",IF(M13="Yes","Returned","Completed")) -> Completed | T13: =F13*(1-G13/100) -> 932.4 | U13: =IF(P13="Late",1,0) -> 0
... A301: O0300 | B301: 46268 | C301: Grocery | D301: Chennai | E301: 52 | F301: 1417 | G301: 20 | H301: 2 | I301: 3 | J301: Credit Card | K301: 4 | L301: No | M301: No | N301: 11.5 | O301: New | P301: =IF(I301>H301,"Late","On Time") -> Late | Q301: =MAX(0,I301-H301) -> 1 | R301: =IF(K301>=4,"High",IF(K301=3,"Medium","Low")) -> High | S301: =IF(L301="Yes","Cancelled",IF(M301="Yes","Returned","Completed")) -> Completed | T301: =F301*(1-G301/100) -> 1133.6 | U301: =IF(P301="Late",1,0) -> 1

Sheet Analysis
A1: E-Commerce Customer Experience Analysis
A3: KPI | B3: Value
A4: Total Orders | B4: =COUNTA('Cleaned Data'!A2:A301) -> 300
A5: Total Net Sales | B5: =SUM('Cleaned Data'!T2:T301) -> 582305.5
A6: Average Rating | B6: =AVERAGE('Cleaned Data'!K2:K301) -> 4.0966667
A7: Late Delivery % | B7: =AVERAGE('Cleaned Data'!U2:U301) -> 0.35333333
A8: Cancellation % | B8: =COUNTIF('Cleaned Data'!L2:L301,"Yes")/B4 -> 0.026666667
A9: Return % | B9: =COUNTIF('Cleaned Data'!M2:M301,"Yes")/B4 -> 0.03
A10: Average Delivery Days | B10: =AVERAGE('Cleaned Data'!I2:I301) -> 2.9766667
A13: Catagory | B13: Total orders | C13: Net Sales | D13: Average Ratings | E13: Average Delivery Days | F13: Late % | H13: City | I13: Avg Delivery Days | J13: Avg Rating | K13: Late %
A14: Electronics | B14: =COUNTIF('Cleaned Data'!C$2:C$301,A14) -> 60 | C14: =SUMIF('Cleaned Data'!C$2:C$301,A14,'Cleaned Data'!T$2:T$301) -> 233466.8 | D14: =AVERAGEIF('Cleaned Data'!C$2:C$301,A14,'Cleaned Data'!K$2:K$301) -> 3.95 | E14: =AVERAGEIF('Cleaned Data'!C$2:C$301,A14,'Cleaned Data'!I$2:I$301) -> 3.4666667 | F14: =AVERAGEIF('Cleaned Data'!C$2:C$301,A14,'Cleaned Data'!U$2:U$301) -> 0.4 | H14: Bengaluru | I14: =AVERAGEIF('Cleaned Data'!D$2:D$301,H14,'Cleaned Data'!I$2:I$301) -> 2.8536585 | J14: =AVERAGEIF('Cleaned Data'!D$2:D$301,H14,'Cleaned Data'!K$2:K$301) -> 4.1463415 | K14: =AVERAGEIF('Cleaned Data'!D$2:D$301,H14,'Cleaned Data'!U$2:U$301) -> 0.36585366
A15: Fashion | B15: =COUNTIF('Cleaned Data'!C$2:C$301,A15) -> 57 | C15: =SUMIF('Cleaned Data'!C$2:C$301,A15,'Cleaned Data'!T$2:T$301) -> 84588.35 | D15: =AVERAGEIF('Cleaned Data'!C$2:C$301,A15,'Cleaned Data'!K$2:K$301) -> 4.1052632 | E15: =AVERAGEIF('Cleaned Data'!C$2:C$301,A15,'Cleaned Data'!I$2:I$301) -> 3.4035088 | F15: =AVERAGEIF('Cleaned Data'!C$2:C$301,A15,'Cleaned Data'!U$2:U$301) -> 0.33333333 | H15: Mumbai | I15: =AVERAGEIF('Cleaned Data'!D$2:D$301,H15,'Cleaned Data'!I$2:I$301) -> 2.9428571 | J15: =AVERAGEIF('Cleaned Data'!D$2:D$301,H15,'Cleaned Data'!K$2:K$301) -> 3.9714286 | K15: =AVERAGEIF('Cleaned Data'!D$2:D$301,H15,'Cleaned Data'!U$2:U$301) -> 0.37142857
A16: Grocery | B16: =COUNTIF('Cleaned Data'!C$2:C$301,A16) -> 66 | C16: =SUMIF('Cleaned Data'!C$2:C$301,A16,'Cleaned Data'!T$2:T$301) -> 52729.85 | D16: =AVERAGEIF('Cleaned Data'!C$2:C$301,A16,'Cleaned Data'!K$2:K$301) -> 4.2272727 | E16: =AVERAGEIF('Cleaned Data'!C$2:C$301,A16,'Cleaned Data'!I$2:I$301) -> 2.3181818 | F16: =AVERAGEIF('Cleaned Data'!C$2:C$301,A16,'Cleaned Data'!U$2:U$301) -> 0.33333333 | H16: Delhi | I16: =AVERAGEIF('Cleaned Data'!D$2:D$301,H16,'Cleaned Data'!I$2:I$301) -> 3.2653061 | J16: =AVERAGEIF('Cleaned Data'!D$2:D$301,H16,'Cleaned Data'!K$2:K$301) -> 4.0612245 | K16: =AVERAGEIF('Cleaned Data'!D$2:D$301,H16,'Cleaned Data'!U$2:U$301) -> 0.42857143
A17: Home & Kitchen | B17: =COUNTIF('Cleaned Data'!C$2:C$301,A17) -> 59 | C17: =SUMIF('Cleaned Data'!C$2:C$301,A17,'Cleaned Data'!T$2:T$301) -> 137168.95 | D17: =AVERAGEIF('Cleaned Data'!C$2:C$301,A17,'Cleaned Data'!K$2:K$301) -> 4.0338983 | E17: =AVERAGEIF('Cleaned Data'!C$2:C$301,A17,'Cleaned Data'!I$2:I$301) -> 3.4237288 | F17: =AVERAGEIF('Cleaned Data'!C$2:C$301,A17,'Cleaned Data'!U$2:U$301) -> 0.37288136 | H17: Hyderabad | I17: =AVERAGEIF('Cleaned Data'!D$2:D$301,H17,'Cleaned Data'!I$2:I$301) -> 3 | J17: =AVERAGEIF('Cleaned Data'!D$2:D$301,H17,'Cleaned Data'!K$2:K$301) -> 3.8863636 | K17: =AVERAGEIF('Cleaned Data'!D$2:D$301,H17,'Cleaned Data'!U$2:U$301) -> 0.34090909
A18: Beauty | B18: =COUNTIF('Cleaned Data'!C$2:C$301,A18) -> 58 | C18: =SUMIF('Cleaned Data'!C$2:C$301,A18,'Cleaned Data'!T$2:T$301) -> 74351.55 | D18: =AVERAGEIF('Cleaned Data'!C$2:C$301,A18,'Cleaned Data'!K$2:K$301) -> 4.1551724 | E18: =AVERAGEIF('Cleaned Data'!C$2:C$301,A18,'Cleaned Data'!I$2:I$301) -> 2.3448276 | F18: =AVERAGEIF('Cleaned Data'!C$2:C$301,A18,'Cleaned Data'!U$2:U$301) -> 0.32758621 | H18: Chennai | I18: =AVERAGEIF('Cleaned Data'!D$2:D$301,H18,'Cleaned Data'!I$2:I$301) -> 3.1 | J18: =AVERAGEIF('Cleaned Data'!D$2:D$301,H18,'Cleaned Data'!K$2:K$301) -> 4.15 | K18: =AVERAGEIF('Cleaned Data'!D$2:D$301,H18,'Cleaned Data'!U$2:U$301) -> 0.35
H19: Pune | I19: =AVERAGEIF('Cleaned Data'!D$2:D$301,H19,'Cleaned Data'!I$2:I$301) -> 2.6857143 | J19: =AVERAGEIF('Cleaned Data'!D$2:D$301,H19,'Cleaned Data'!K$2:K$301) -> 4.3142857 | K19: =AVERAGEIF('Cleaned Data'!D$2:D$301,H19,'Cleaned Data'!U$2:U$301) -> 0.22857143
H20: Kolkata | I20: =AVERAGEIF('Cleaned Data'!D$2:D$301,H20,'Cleaned Data'!I$2:I$301) -> 2.9107143 | J20: =AVERAGEIF('Cleaned Data'!D$2:D$301,H20,'Cleaned Data'!K$2:K$301) -> 4.1607143 | K20: =AVERAGEIF('Cleaned Data'!D$2:D$301,H20,'Cleaned Data'!U$2:U$301) -> 0.35714286
A21: Delivery Status | B21: Average Rating
A22: ON TIME | B22: =AVERAGEIF('Cleaned Data'!P$2:P$301,A22,'Cleaned Data'!K$2:K$301) -> 4.4896907
A23: Late | B23: =AVERAGEIF('Cleaned Data'!P$2:P$301,A23,'Cleaned Data'!K$2:K$301) -> 3.3773585

Sheet Dashboard
A1: TOTAL ORDERS | B1: NET SALES | C1: AVG RATING | D1: LATE DELIVERY % | E1: CANCEL RATE | F1: RETURN RATE
A2: =Analysis!B4 -> 300 | B2: =Analysis!B5 -> 582305.5 | C2: =Analysis!B6 -> 4.0966667 | D2: =Analysis!B7 -> 0.35333333 | E2: =Analysis!B8 -> 0.026666667 | F2: =Analysis!B9 -> 0.03
